{
  "updated": "2026-07-08 01:13 KST",
  "total": 16,
  "success": 14,
  "etfs": [
    {
      "id": "e01",
      "code": "314250",
      "name": "KODEX 미국빅테크10(H)",
      "cat": "us",
      "dist": "",
      "price": "57810",
      "chg": "",
      "chg_dir": "flat",
      "nav": "",
      "aum": "",
      "w52_high": "",
      "w52_low": "",
      "per": "",
      "pbr": "",
      "updated": "2026-07-08 01:13 KST",
      "fetch_ok": true
    },
    {
      "id": "e02",
      "code": "396500",
      "name": "TIGER 반도체TOP10",
      "cat": "kr",
      "dist": "",
      "price": "41375",
      "chg": "",
      "chg_dir": "flat",
      "nav": "",
      "aum": "",
      "w52_high": "",
      "w52_low": "",
      "per": "",
      "pbr": "",
      "updated": "2026-07-08 01:13 KST",
      "fetch_ok": true
    },
    {
      "id": "e03",
      "code": "0173Y0",
      "name": "KODEX 미국AI광통신네트워크",
      "cat": "us",
      "dist": "",
      "price": "12650",
      "chg": "",
      "chg_dir": "flat",
      "nav": "",
      "aum": "",
      "w52_high": "",
      "w52_low": "",
      "per": "",
      "pbr": "",
      "updated": "2026-07-08 01:13 KST",
      "fetch_ok": true
    },
    {
      "id": "e04",
      "code": "458730",
      "name": "TIGER 미국배당다우존스",
      "cat": "div",
      "dist": "",
      "price": "15710",
      "chg": "",
      "chg_dir": "flat",
      "nav": "",
      "aum": "",
      "w52_high": "",
      "w52_low": "",
      "per": "",
      "pbr": "",
      "updated": "2026-07-08 01:13 KST",
      "fetch_ok": true
    },
    {
      "id": "e05",
      "code": "441640",
      "name": "KODEX 미국배당커버드콜액티브",
      "cat": "div",
      "dist": "",
      "price": "13675",
      "chg": "",
      "chg_dir": "flat",
      "nav": "",
      "aum": "",
      "w52_high": "",
      "w52_low": "",
      "per": "",
      "pbr": "",
      "updated": "2026-07-08 01:13 KST",
      "fetch_ok": true
    },
    {
      "id": "e06",
      "code": "395400",
      "name": "KODEX 한국부동산리츠인프라",
      "cat": "re",
      "dist": "",
      "price": "5920",
      "chg": "",
      "chg_dir": "flat",
      "nav": "",
      "aum": "",
      "w52_high": "",
      "w52_low": "",
      "per": "",
      "pbr": "",
      "updated": "2026-07-08 01:13 KST",
      "fetch_ok": true
    },
    {
      "id": "e07",
      "code": "494300",
      "name": "KODEX 나스닥100데일리커버드콜OTM",
      "cat": "cc",
      "dist": "",
      "price": "10480",
      "chg": "",
      "chg_dir": "flat",
      "nav": "",
      "aum": "",
      "w52_high": "",
      "w52_low": "",
      "per": "",
      "pbr": "",
      "updated": "2026-07-08 01:13 KST",
      "fetch_ok": true
    },
    {
      "id": "e08",
      "code": "498410",
      "name": "KODEX 금융고배당TOP10위클리커버드콜",
      "cat": "cc",
      "dist": "",
      "price": "12125",
      "chg": "",
      "chg_dir": "flat",
      "nav": "",
      "aum": "",
      "w52_high": "",
      "w52_low": "",
      "per": "",
      "pbr": "",
      "updated": "2026-07-08 01:13 KST",
      "fetch_ok": true
    },
    {
      "id": "e09",
      "code": "0167A0",
      "name": "SOL AI반도체TOP2플러스",
      "cat": "kr",
      "dist": "",
      "price": "21470",
      "chg": "",
      "chg_dir": "flat",
      "nav": "",
      "aum": "",
      "w52_high": "",
      "w52_low": "",
      "per": "",
      "pbr": "",
      "updated": "2026-07-08 01:13 KST",
      "fetch_ok": true
    },
    {
      "id": "e10",
      "code": "0190C0",
      "name": "RISE 현대차고정피지컬AI",
      "cat": "kr",
      "dist": "",
      "price": "9465",
      "chg": "",
      "chg_dir": "flat",
      "nav": "",
      "aum": "",
      "w52_high": "",
      "w52_low": "",
      "per": "",
      "pbr": "",
      "updated": "2026-07-08 01:13 KST",
      "fetch_ok": true
    },
    {
      "id": "e11",
      "code": "489030",
      "name": "PLUS 고배당주위클리커버드콜",
      "cat": "cc",
      "dist": "",
      "price": "6565",
      "chg": "",
      "chg_dir": "flat",
      "nav": "",
      "aum": "",
      "w52_high": "",
      "w52_low": "",
      "per": "",
      "pbr": "",
      "updated": "2026-07-08 01:13 KST",
      "fetch_ok": true
    },
    {
      "id": "e12",
      "code": "483570",
      "name": "KODEX 방산TOP10",
      "cat": "kr",
      "dist": "",
      "price": "16455",
      "chg": "",
      "chg_dir": "flat",
      "nav": "",
      "aum": "",
      "w52_high": "",
      "w52_low": "",
      "per": "",
      "pbr": "",
      "updated": "2026-07-08 01:13 KST",
      "fetch_ok": true
    },
    {
      "id": "e13",
      "code": "0190D0",
      "name": "RISE AI전력인프라",
      "cat": "kr",
      "dist": "",
      "price": "",
      "chg": "",
      "chg_dir": "up",
      "nav": "",
      "aum": "",
      "w52_high": "",
      "w52_low": "",
      "per": "",
      "pbr": "",
      "updated": "2026-07-08 01:13 KST",
      "fetch_ok": false
    },
    {
      "id": "e14",
      "code": "491290",
      "name": "KODEX 조선TOP10",
      "cat": "kr",
      "dist": "",
      "price": "",
      "chg": "",
      "chg_dir": "up",
      "nav": "",
      "aum": "",
      "w52_high": "",
      "w52_low": "",
      "per": "",
      "pbr": "",
      "updated": "2026-07-08 01:13 KST",
      "fetch_ok": false
    },
    {
      "id": "e15",
      "code": "305720",
      "name": "KODEX 2차전지산업",
      "cat": "kr",
      "dist": "",
      "price": "13595",
      "chg": "",
      "chg_dir": "flat",
      "nav": "",
      "aum": "",
      "w52_high": "",
      "w52_low": "",
      "per": "",
      "pbr": "",
      "updated": "2026-07-08 01:13 KST",
      "fetch_ok": true
    },
    {
      "id": "e16",
      "code": "483280",
      "name": "KODEX 미국AI테크TOP10타겟커버드콜",
      "cat": "cc",
      "dist": "",
      "price": "12720",
      "chg": "",
      "chg_dir": "flat",
      "nav": "",
      "aum": "",
      "w52_high": "",
      "w52_low": "",
      "per": "",
      "pbr": "",
      "updated": "2026-07-08 01:13 KST",
      "fetch_ok": true
    }
  ]
}